detransliterator/__about__.py
detransliterator/__init__.py
detransliterator/csv_tool.py
detransliterator/detransliterator.py
detransliterator/tool.py
detransliterator/utils.py
detransliterator/assets/latin2nqo_001.35/checkpoints/checkpoint_best.pt
detransliterator/assets/latin2nqo_001.35/data/bpe.code
detransliterator/assets/latin2nqo_001.35/data/dict.nqo.txt
detransliterator/assets/latin2nqo_001.35/data/dict.roman.txt
detransliterator/assets/latin2nqo_001.38/checkpoints/checkpoint_best.pt
detransliterator/assets/latin2nqo_001.38/data/bpe.code
detransliterator/assets/latin2nqo_001.38/data/dict.nqo.txt
detransliterator/assets/latin2nqo_001.38/data/dict.roman.txt
detransliterator/assets/test_data/diane_parallel_002.bam-g
detransliterator/assets/test_data/diane_parallel_002.bam-g-tonal
detransliterator/assets/test_data/diane_parallel_002.bam-k
detransliterator/assets/test_data/diane_parallel_002.bam-k-tonal
detransliterator/assets/test_data/diane_parallel_002.emk
detransliterator/assets/test_data/diane_parallel_002.emk-tonal
detransliterator/assets/test_data/diane_parallel_002.nqo
detransliterator/assets/test_data/test_csv_no_header.csv
detransliterator/assets/test_data/test_csv_with_header.csv
detransliterator/assets/test_data/test_tsv_no_header.tsv
detransliterator/assets/test_data/test_tsv_with_header.tsv
detransliterator-0.0.2.dist-info/METADATA
detransliterator-0.0.2.dist-info/WHEEL
detransliterator-0.0.2.dist-info/licenses/LICENSE.txt
detransliterator-0.0.2.dist-info/RECORD
