Metadata-Version: 2.1
Name: detransliterator
Version: 0.0.2
Project-URL: Documentation, https://github.com/mdoumbouya/detransliterator#readme
Project-URL: Issues, https://github.com/mdoumbouya/detransliterator/issues
Project-URL: Source, https://github.com/mdoumbouya/detransliterator
Author-email: Moussa Doumbouya <doumbouya.moussa@gmail.com>
Classifier: Development Status :: 4 - Beta
Classifier: Programming Language :: Python
Classifier: Programming Language :: Python :: 3.10
Classifier: Programming Language :: Python :: 3.7
Classifier: Programming Language :: Python :: 3.8
Classifier: Programming Language :: Python :: 3.9
Classifier: Programming Language :: Python :: Implementation :: CPython
Classifier: Programming Language :: Python :: Implementation :: PyPy
Classifier: Topic :: Scientific/Engineering :: Artificial Intelligence
Requires-Python: >=3.7
Requires-Dist: fairseq
Requires-Dist: sacremoses==0.0.49
Requires-Dist: subword-nmt==0.3.8
